telegram_agent_bot/__init__.py
telegram_agent_bot/client.py
telegram_agent_bot-0.1.0.dist-info/LICENSE
telegram_agent_bot-0.1.0.dist-info/METADATA
telegram_agent_bot-0.1.0.dist-info/WHEEL
telegram_agent_bot-0.1.0.dist-info/top_level.txt
telegram_agent_bot-0.1.0.dist-info/RECORD
