Metadata-Version: 2.1
Name: telegram_agent_bot
Version: 0.1.0
Summary: Wrapper For Geminin Agents
Author: Viacheslav Kovalevskyi
Author-email: viacheslav@kovalevskyi.com
License: MIT
License-File: LICENSE
Requires-Dist: python-telegram-bot ==21.6
Requires-Dist: requests ==2.32.*
